LICENSE.md
MANIFEST.in
README.rst
pyproject.toml
requirements.core.txt
setup.py
core_curate_app/__init__.py
core_curate_app/admin.py
core_curate_app/apps.py
core_curate_app/menus.py
core_curate_app/models.py
core_curate_app/settings.py
core_curate_app/urls.py
core_curate_app.egg-info/PKG-INFO
core_curate_app.egg-info/SOURCES.txt
core_curate_app.egg-info/dependency_links.txt
core_curate_app.egg-info/requires.txt
core_curate_app.egg-info/top_level.txt
core_curate_app/access_control/__init__.py
core_curate_app/access_control/api.py
core_curate_app/common/__init__.py
core_curate_app/common/exceptions.py
core_curate_app/components/__init__.py
core_curate_app/components/curate_data_structure/__init__.py
core_curate_app/components/curate_data_structure/admin_site.py
core_curate_app/components/curate_data_structure/api.py
core_curate_app/components/curate_data_structure/models.py
core_curate_app/migrations/0001_initial.py
core_curate_app/migrations/__init__.py
core_curate_app/permissions/__init__.py
core_curate_app/permissions/discover.py
core_curate_app/permissions/rights.py
core_curate_app/rest/__init__.py
core_curate_app/rest/urls.py
core_curate_app/rest/curate_data_structure/__init__.py
core_curate_app/rest/curate_data_structure/admin_serializers.py
core_curate_app/rest/curate_data_structure/serializers.py
core_curate_app/rest/curate_data_structure/views.py
core_curate_app/static/core_curate_app/user/css/common.css
core_curate_app/static/core_curate_app/user/css/json_form.css
core_curate_app/static/core_curate_app/user/css/style.css
core_curate_app/static/core_curate_app/user/css/xsd_form.css
core_curate_app/static/core_curate_app/user/img/collapse.png
core_curate_app/static/core_curate_app/user/img/expand.png
core_curate_app/static/core_curate_app/user/js/buttons.raw.js
core_curate_app/static/core_curate_app/user/js/choice.raw.js
core_curate_app/static/core_curate_app/user/js/enter_data.js
core_curate_app/static/core_curate_app/user/js/enter_data.raw.js
core_curate_app/static/core_curate_app/user/js/select_template.js
core_curate_app/static/core_curate_app/user/js/select_template.raw.js
core_curate_app/static/core_curate_app/user/js/switch_editor.js
