Metadata-Version: 2.1
Name: core-curate-app
Version: 2.19.0
Summary: Curation functionalities for the curator core project
Home-page: https://github.com/usnistgov/core_curate_app
Author: NIST IT Lab
Author-email: itl_inquiries@nist.gov
License-File: LICENSE.md
